r_capture-0.1.1.dist-info/METADATA
r_capture-0.1.1.dist-info/WHEEL
r_capture/__init__.py
r_capture/__init__.pyi
r_capture/py.typed
r_capture/r_capture.cp311-win_amd64.pyd
r_capture-0.1.1.dist-info/RECORD
