Metadata-Version: 2.4
Name: r_capture
Version: 0.1.1
Classifier: Programming Language :: Rust
Classifier: Programming Language :: Python :: Implementation :: CPython
Classifier: Programming Language :: Python :: Implementation :: PyPy
Summary: A simple lib for capture your window screen
License: MIT
Requires-Python: >=3.8
